<?xml version="1.0"?>
<!DOCTYPE wallpapers SYSTEM "gnome-wp-list.dtd">
<wallpapers>
  <wallpaper>
    <name>forest road</name>
    <filename>/usr/share/backgrounds/budgie/forest_road_by_monika_murren.jpg</filename>
    <options>zoom</options>
    <pcolor>#000000</pcolor>
    <scolor>#000000</scolor>
    <shade_type>solid</shade_type>
  </wallpaper>
  <wallpaper>
    <name>outdoor mineral pool</name>
    <filename>/usr/share/backgrounds/budgie/outdoor-mineral-pool_by_brodie_vissers.jpg</filename>
    <options>zoom</options>
    <pcolor>#000000</pcolor>
    <scolor>#000000</scolor>
    <shade_type>solid</shade_type>
  </wallpaper>
  <wallpaper>
    <name>tunnel urban path</name>
    <filename>/usr/share/backgrounds/budgie/tunnel-urban-path_by_mitul_shah.jpg</filename>
    <options>zoom</options>
    <pcolor>#000000</pcolor>
    <scolor>#000000</scolor>
    <shade_type>solid</shade_type>
  </wallpaper>
  <wallpaper>
    <name>train trip</name>
    <filename>/usr/share/backgrounds/budgie/train_trip_by_georgie_pauwels.jpg</filename>
    <options>zoom</options>
    <pcolor>#000000</pcolor>
    <scolor>#000000</scolor>
    <shade_type>solid</shade_type>
  </wallpaper>
  <wallpaper>
    <name>people walk on bright beach</name>
    <filename>/usr/share/backgrounds/budgie/people-walk-on-bright-beach_by_brodie_vissers.jpg</filename>
    <options>zoom</options>
    <pcolor>#000000</pcolor>
    <scolor>#000000</scolor>
    <shade_type>solid</shade_type>
  </wallpaper>
  <wallpaper>
    <name>sports 5 6</name>
    <filename>/usr/share/backgrounds/budgie/sports_5_6_by_matt_moloney.jpg</filename>
    <options>zoom</options>
    <pcolor>#000000</pcolor>
    <scolor>#000000</scolor>
    <shade_type>solid</shade_type>
  </wallpaper>
  <wallpaper>
    <name>water and coffee</name>
    <filename>/usr/share/backgrounds/budgie/water_and_coffee_by_alexey_dulin.jpg</filename>
    <options>zoom</options>
    <pcolor>#000000</pcolor>
    <scolor>#000000</scolor>
    <shade_type>solid</shade_type>
  </wallpaper>
  <wallpaper>
    <name>mirror walk</name>
    <filename>/usr/share/backgrounds/budgie/mirror_walk_by_georgie_pauwels.jpg</filename>
    <options>zoom</options>
    <pcolor>#000000</pcolor>
    <scolor>#000000</scolor>
    <shade_type>solid</shade_type>
  </wallpaper>
</wallpapers>
